{
	"backtraceGraph" : 
	{
		"commands" : 
		[
			"install"
		],
		"files" : 
		[
			"mbedtls/programs/pkey/CMakeLists.txt"
		],
		"nodes" : 
		[
			{
				"file" : 0
			},
			{
				"command" : 0,
				"file" : 0,
				"line" : 41,
				"parent" : 0
			}
		]
	},
	"installers" : 
	[
		{
			"backtrace" : 1,
			"component" : "Unspecified",
			"destination" : "bin",
			"paths" : 
			[
				"mbedtls/programs/pkey/dh_client.exe"
			],
			"targetId" : "dh_client::@71b4baed6449711a7760",
			"targetIndex" : 10,
			"type" : "target"
		},
		{
			"backtrace" : 1,
			"component" : "Unspecified",
			"cxxModuleBmiTarget" : 
			{
				"id" : "dh_client::@71b4baed6449711a7760",
				"index" : 10
			},
			"destination" : "bin",
			"type" : "cxxModuleBmi"
		},
		{
			"backtrace" : 1,
			"component" : "Unspecified",
			"destination" : "bin",
			"paths" : 
			[
				"mbedtls/programs/pkey/dh_server.exe"
			],
			"targetId" : "dh_server::@71b4baed6449711a7760",
			"targetIndex" : 12,
			"type" : "target"
		},
		{
			"backtrace" : 1,
			"component" : "Unspecified",
			"cxxModuleBmiTarget" : 
			{
				"id" : "dh_server::@71b4baed6449711a7760",
				"index" : 12
			},
			"destination" : "bin",
			"type" : "cxxModuleBmi"
		},
		{
			"backtrace" : 1,
			"component" : "Unspecified",
			"destination" : "bin",
			"paths" : 
			[
				"mbedtls/programs/pkey/dh_genprime.exe"
			],
			"targetId" : "dh_genprime::@71b4baed6449711a7760",
			"targetIndex" : 11,
			"type" : "target"
		},
		{
			"backtrace" : 1,
			"component" : "Unspecified",
			"cxxModuleBmiTarget" : 
			{
				"id" : "dh_genprime::@71b4baed6449711a7760",
				"index" : 11
			},
			"destination" : "bin",
			"type" : "cxxModuleBmi"
		},
		{
			"backtrace" : 1,
			"component" : "Unspecified",
			"destination" : "bin",
			"paths" : 
			[
				"mbedtls/programs/pkey/ecdh_curve25519.exe"
			],
			"targetId" : "ecdh_curve25519::@71b4baed6449711a7760",
			"targetIndex" : 15,
			"type" : "target"
		},
		{
			"backtrace" : 1,
			"component" : "Unspecified",
			"cxxModuleBmiTarget" : 
			{
				"id" : "ecdh_curve25519::@71b4baed6449711a7760",
				"index" : 15
			},
			"destination" : "bin",
			"type" : "cxxModuleBmi"
		},
		{
			"backtrace" : 1,
			"component" : "Unspecified",
			"destination" : "bin",
			"paths" : 
			[
				"mbedtls/programs/pkey/ecdsa.exe"
			],
			"targetId" : "ecdsa::@71b4baed6449711a7760",
			"targetIndex" : 16,
			"type" : "target"
		},
		{
			"backtrace" : 1,
			"component" : "Unspecified",
			"cxxModuleBmiTarget" : 
			{
				"id" : "ecdsa::@71b4baed6449711a7760",
				"index" : 16
			},
			"destination" : "bin",
			"type" : "cxxModuleBmi"
		},
		{
			"backtrace" : 1,
			"component" : "Unspecified",
			"destination" : "bin",
			"paths" : 
			[
				"mbedtls/programs/pkey/gen_key.exe"
			],
			"targetId" : "gen_key::@71b4baed6449711a7760",
			"targetIndex" : 19,
			"type" : "target"
		},
		{
			"backtrace" : 1,
			"component" : "Unspecified",
			"cxxModuleBmiTarget" : 
			{
				"id" : "gen_key::@71b4baed6449711a7760",
				"index" : 19
			},
			"destination" : "bin",
			"type" : "cxxModuleBmi"
		},
		{
			"backtrace" : 1,
			"component" : "Unspecified",
			"destination" : "bin",
			"paths" : 
			[
				"mbedtls/programs/pkey/key_app.exe"
			],
			"targetId" : "key_app::@71b4baed6449711a7760",
			"targetIndex" : 24,
			"type" : "target"
		},
		{
			"backtrace" : 1,
			"component" : "Unspecified",
			"cxxModuleBmiTarget" : 
			{
				"id" : "key_app::@71b4baed6449711a7760",
				"index" : 24
			},
			"destination" : "bin",
			"type" : "cxxModuleBmi"
		},
		{
			"backtrace" : 1,
			"component" : "Unspecified",
			"destination" : "bin",
			"paths" : 
			[
				"mbedtls/programs/pkey/key_app_writer.exe"
			],
			"targetId" : "key_app_writer::@71b4baed6449711a7760",
			"targetIndex" : 25,
			"type" : "target"
		},
		{
			"backtrace" : 1,
			"component" : "Unspecified",
			"cxxModuleBmiTarget" : 
			{
				"id" : "key_app_writer::@71b4baed6449711a7760",
				"index" : 25
			},
			"destination" : "bin",
			"type" : "cxxModuleBmi"
		},
		{
			"backtrace" : 1,
			"component" : "Unspecified",
			"destination" : "bin",
			"paths" : 
			[
				"mbedtls/programs/pkey/mpi_demo.exe"
			],
			"targetId" : "mpi_demo::@71b4baed6449711a7760",
			"targetIndex" : 37,
			"type" : "target"
		},
		{
			"backtrace" : 1,
			"component" : "Unspecified",
			"cxxModuleBmiTarget" : 
			{
				"id" : "mpi_demo::@71b4baed6449711a7760",
				"index" : 37
			},
			"destination" : "bin",
			"type" : "cxxModuleBmi"
		},
		{
			"backtrace" : 1,
			"component" : "Unspecified",
			"destination" : "bin",
			"paths" : 
			[
				"mbedtls/programs/pkey/pk_encrypt.exe"
			],
			"targetId" : "pk_encrypt::@71b4baed6449711a7760",
			"targetIndex" : 41,
			"type" : "target"
		},
		{
			"backtrace" : 1,
			"component" : "Unspecified",
			"cxxModuleBmiTarget" : 
			{
				"id" : "pk_encrypt::@71b4baed6449711a7760",
				"index" : 41
			},
			"destination" : "bin",
			"type" : "cxxModuleBmi"
		},
		{
			"backtrace" : 1,
			"component" : "Unspecified",
			"destination" : "bin",
			"paths" : 
			[
				"mbedtls/programs/pkey/pk_decrypt.exe"
			],
			"targetId" : "pk_decrypt::@71b4baed6449711a7760",
			"targetIndex" : 40,
			"type" : "target"
		},
		{
			"backtrace" : 1,
			"component" : "Unspecified",
			"cxxModuleBmiTarget" : 
			{
				"id" : "pk_decrypt::@71b4baed6449711a7760",
				"index" : 40
			},
			"destination" : "bin",
			"type" : "cxxModuleBmi"
		},
		{
			"backtrace" : 1,
			"component" : "Unspecified",
			"destination" : "bin",
			"paths" : 
			[
				"mbedtls/programs/pkey/pk_sign.exe"
			],
			"targetId" : "pk_sign::@71b4baed6449711a7760",
			"targetIndex" : 42,
			"type" : "target"
		},
		{
			"backtrace" : 1,
			"component" : "Unspecified",
			"cxxModuleBmiTarget" : 
			{
				"id" : "pk_sign::@71b4baed6449711a7760",
				"index" : 42
			},
			"destination" : "bin",
			"type" : "cxxModuleBmi"
		},
		{
			"backtrace" : 1,
			"component" : "Unspecified",
			"destination" : "bin",
			"paths" : 
			[
				"mbedtls/programs/pkey/pk_verify.exe"
			],
			"targetId" : "pk_verify::@71b4baed6449711a7760",
			"targetIndex" : 43,
			"type" : "target"
		},
		{
			"backtrace" : 1,
			"component" : "Unspecified",
			"cxxModuleBmiTarget" : 
			{
				"id" : "pk_verify::@71b4baed6449711a7760",
				"index" : 43
			},
			"destination" : "bin",
			"type" : "cxxModuleBmi"
		},
		{
			"backtrace" : 1,
			"component" : "Unspecified",
			"destination" : "bin",
			"paths" : 
			[
				"mbedtls/programs/pkey/rsa_decrypt.exe"
			],
			"targetId" : "rsa_decrypt::@71b4baed6449711a7760",
			"targetIndex" : 50,
			"type" : "target"
		},
		{
			"backtrace" : 1,
			"component" : "Unspecified",
			"cxxModuleBmiTarget" : 
			{
				"id" : "rsa_decrypt::@71b4baed6449711a7760",
				"index" : 50
			},
			"destination" : "bin",
			"type" : "cxxModuleBmi"
		},
		{
			"backtrace" : 1,
			"component" : "Unspecified",
			"destination" : "bin",
			"paths" : 
			[
				"mbedtls/programs/pkey/rsa_encrypt.exe"
			],
			"targetId" : "rsa_encrypt::@71b4baed6449711a7760",
			"targetIndex" : 51,
			"type" : "target"
		},
		{
			"backtrace" : 1,
			"component" : "Unspecified",
			"cxxModuleBmiTarget" : 
			{
				"id" : "rsa_encrypt::@71b4baed6449711a7760",
				"index" : 51
			},
			"destination" : "bin",
			"type" : "cxxModuleBmi"
		},
		{
			"backtrace" : 1,
			"component" : "Unspecified",
			"destination" : "bin",
			"paths" : 
			[
				"mbedtls/programs/pkey/rsa_genkey.exe"
			],
			"targetId" : "rsa_genkey::@71b4baed6449711a7760",
			"targetIndex" : 52,
			"type" : "target"
		},
		{
			"backtrace" : 1,
			"component" : "Unspecified",
			"cxxModuleBmiTarget" : 
			{
				"id" : "rsa_genkey::@71b4baed6449711a7760",
				"index" : 52
			},
			"destination" : "bin",
			"type" : "cxxModuleBmi"
		},
		{
			"backtrace" : 1,
			"component" : "Unspecified",
			"destination" : "bin",
			"paths" : 
			[
				"mbedtls/programs/pkey/rsa_sign.exe"
			],
			"targetId" : "rsa_sign::@71b4baed6449711a7760",
			"targetIndex" : 53,
			"type" : "target"
		},
		{
			"backtrace" : 1,
			"component" : "Unspecified",
			"cxxModuleBmiTarget" : 
			{
				"id" : "rsa_sign::@71b4baed6449711a7760",
				"index" : 53
			},
			"destination" : "bin",
			"type" : "cxxModuleBmi"
		},
		{
			"backtrace" : 1,
			"component" : "Unspecified",
			"destination" : "bin",
			"paths" : 
			[
				"mbedtls/programs/pkey/rsa_sign_pss.exe"
			],
			"targetId" : "rsa_sign_pss::@71b4baed6449711a7760",
			"targetIndex" : 54,
			"type" : "target"
		},
		{
			"backtrace" : 1,
			"component" : "Unspecified",
			"cxxModuleBmiTarget" : 
			{
				"id" : "rsa_sign_pss::@71b4baed6449711a7760",
				"index" : 54
			},
			"destination" : "bin",
			"type" : "cxxModuleBmi"
		},
		{
			"backtrace" : 1,
			"component" : "Unspecified",
			"destination" : "bin",
			"paths" : 
			[
				"mbedtls/programs/pkey/rsa_verify.exe"
			],
			"targetId" : "rsa_verify::@71b4baed6449711a7760",
			"targetIndex" : 55,
			"type" : "target"
		},
		{
			"backtrace" : 1,
			"component" : "Unspecified",
			"cxxModuleBmiTarget" : 
			{
				"id" : "rsa_verify::@71b4baed6449711a7760",
				"index" : 55
			},
			"destination" : "bin",
			"type" : "cxxModuleBmi"
		},
		{
			"backtrace" : 1,
			"component" : "Unspecified",
			"destination" : "bin",
			"paths" : 
			[
				"mbedtls/programs/pkey/rsa_verify_pss.exe"
			],
			"targetId" : "rsa_verify_pss::@71b4baed6449711a7760",
			"targetIndex" : 56,
			"type" : "target"
		},
		{
			"backtrace" : 1,
			"component" : "Unspecified",
			"cxxModuleBmiTarget" : 
			{
				"id" : "rsa_verify_pss::@71b4baed6449711a7760",
				"index" : 56
			},
			"destination" : "bin",
			"type" : "cxxModuleBmi"
		}
	],
	"paths" : 
	{
		"build" : "mbedtls/programs/pkey",
		"source" : "mbedtls/programs/pkey"
	}
}
